LICENSE
MANIFEST.in
README.rst
setup.py
djangocms_section.egg-info/PKG-INFO
djangocms_section.egg-info/SOURCES.txt
djangocms_section.egg-info/dependency_links.txt
djangocms_section.egg-info/top_level.txt
section/__init__.py
section/cms_plugins.py
section/conf.py
section/models.py
section/locale/de/LC_MESSAGES/django.mo
section/locale/de/LC_MESSAGES/django.po
section/migrations/0001_initial.py
section/migrations/__init__.py
section/templates/section/default.html
section/tests/__init__.py
section/tests/tests.py