Metadata-Version: 1.1
Name: djangocms-section
Version: 0.1
Summary: A Django CMS plugin for displaying a FilerImage and a TextPlugin together by means of selectabletemplate layouts.
Home-page: https://github.com/febsn/djangocms-section
Author: Fabian Lehner
Author-email: fl@makonis.net
License: BSD License
Platform: UNKNOWN
Classifier: Environment :: Web Environment
Classifier: Framework :: Django
Classifier: Framework :: Django :: 1.8
Classifier: Intended Audience :: Developers
Classifier: License :: OSI Approved :: BSD License
Classifier: Operating System :: OS Independent
Classifier: Programming Language :: Python
Classifier: Programming Language :: Python :: 2.7
Classifier: Programming Language :: Python :: 3
Classifier: Programming Language :: Python :: 3.4
Classifier: Programming Language :: Python :: 3.5
Classifier: Topic :: Internet :: WWW/HTTP
Classifier: Topic :: Internet :: WWW/HTTP :: Dynamic Content
